pynooj/__init__.py
pynooj/main.py
pynooj-0.1.4.dist-info/WHEEL
pynooj-0.1.4.dist-info/METADATA
pynooj-0.1.4.dist-info/RECORD
