Metadata-Version: 2.3
Name: pynooj
Version: 0.1.4
Summary: Python librairy for parsing NooJ's dictionary files
Keywords: nlp,nooj,linguistics
Author: Morgane Bona-Pellissier
Author-email: Morgane Bona-Pellissier <morgane@bona-pellissier.net>
Requires-Python: >=3.11
Project-URL: Bug Tracker, https://github.com/crispyfunicular/pynooj/issues
Project-URL: Homepage, https://github.com/crispyfunicular/pynooj
